nbscuid/__init__.py
nbscuid/_jupyter-book-config-defaults.yml
nbscuid/build.py
nbscuid/dev-environment.yml
nbscuid/quickstart.py
nbscuid/read.py
nbscuid/run.py
nbscuid/util.py
nbscuid-0.0.10.dist-info/.ipynb_checkpoints/entry_points-checkpoint.txt
nbscuid-0.0.10.dist-info/.ipynb_checkpoints/requires-checkpoint.txt
nbscuid-0.0.10.dist-info/LICENSE
nbscuid-0.0.10.dist-info/METADATA
nbscuid-0.0.10.dist-info/WHEEL
nbscuid-0.0.10.dist-info/entry_points.txt
nbscuid-0.0.10.dist-info/top_level.txt
nbscuid-0.0.10.dist-info/RECORD
