Metadata-Version: 2.1
Name: nbscuid
Version: 0.0.10
Summary: Notebook-Based, Super CUstomizable Infrastructure for Diagnostics
Author-email: Elena Romashkova <eromashkova@ucar.edu>
License: Copyright (c) 2018 The Python Packaging Authority
Project-URL: repository, https://github.com/rmshkv/nbscuid
Project-URL: documentation, https://nbscuid.readthedocs.io
Classifier: Programming Language :: Python :: 3
Classifier: License :: OSI Approved :: MIT License
Requires-Python: >=3.9
License-File: LICENSE
Requires-Dist: black
Requires-Dist: dask
Requires-Dist: dask-jobqueue
Requires-Dist: intake
Requires-Dist: intake-esm
Requires-Dist: jinja2
Requires-Dist: jupyter-book
Requires-Dist: pandas
Requires-Dist: papermill
Requires-Dist: xarray
Requires-Dist: pyyaml
Requires-Dist: ploomber ==0.22.3
